NightWindDataLib/__init__.py
NightWindDataLib/cipher/__init__.py
NightWindDataLib/cipher/curve.py
NightWindDataLib/cipher/images.py
NightWindDataLib/cipher/letter.py
NightWindDataLib/cipher/morse.py
NightWindDataLib/cipher/multiplication.py
NightWindDataLib/cipher/pigpen.py
NightWindDataLib/cipher/virginia.py
NightWindDataLib/cipher/images_image/加密.png
NightWindDataLib/cipher/images_image/图片.png
NightWindDataLib/cipher/images_image/解密后.png
NightWindDataLib/cipher/images_letter/信.png
NightWindDataLib/cipher/images_letter/密码卡.png
NightWindDataLib/cipher/images_morse/di.wav
NightWindDataLib/cipher/images_morse/do.wav
NightWindDataLib/cipher/images_morse/morse.json
NightWindDataLib/cipher/images_pigpen/a.png
NightWindDataLib/cipher/images_pigpen/b.png
NightWindDataLib/cipher/images_pigpen/c.png
NightWindDataLib/cipher/images_pigpen/d.png
NightWindDataLib/cipher/images_pigpen/e.png
NightWindDataLib/cipher/images_pigpen/f.png
NightWindDataLib/cipher/images_pigpen/g.png
NightWindDataLib/cipher/images_pigpen/h.png
NightWindDataLib/cipher/images_pigpen/i.png
NightWindDataLib/cipher/images_pigpen/j.png
NightWindDataLib/cipher/images_pigpen/k.png
NightWindDataLib/cipher/images_pigpen/l.png
NightWindDataLib/cipher/images_pigpen/m.png
NightWindDataLib/cipher/images_pigpen/n.png
NightWindDataLib/cipher/images_pigpen/o.png
NightWindDataLib/cipher/images_pigpen/p.png
NightWindDataLib/cipher/images_pigpen/q.png
NightWindDataLib/cipher/images_pigpen/r.png
NightWindDataLib/cipher/images_pigpen/s.png
NightWindDataLib/cipher/images_pigpen/screenshot.png
NightWindDataLib/cipher/images_pigpen/space.png
NightWindDataLib/cipher/images_pigpen/t.png
NightWindDataLib/cipher/images_pigpen/u.png
NightWindDataLib/cipher/images_pigpen/v.png
NightWindDataLib/cipher/images_pigpen/w.png
NightWindDataLib/cipher/images_pigpen/x.png
NightWindDataLib/cipher/images_pigpen/y.png
NightWindDataLib/cipher/images_pigpen/z.png
NightWindDataLib/cipher/images_virginia/bg.gif
NightWindDataLib/d1/__init__.py
NightWindDataLib-0.1.0.dist-info/METADATA
NightWindDataLib-0.1.0.dist-info/WHEEL
NightWindDataLib-0.1.0.dist-info/top_level.txt
NightWindDataLib-0.1.0.dist-info/RECORD
