Metadata-Version: 2.1
Name: NightWindDataLib
Version: 0.1.0
Summary: Some little games
Home-page: https://github.com
Author: Nova_NightWind0311
Author-email: nova_nightwind0311@qq.com
License: UNKNOWN
Platform: UNKNOWN
Classifier: Programming Language :: Python :: 3
Classifier: License :: OSI Approved :: MIT License
Classifier: Operating System :: OS Independent
